boreflow/__init__.py
boreflow/enum.py
boreflow/finite_volume_method.py
boreflow/geometry.py
boreflow/simulation.py
boreflow/boundary_conditions/__init__.py
boreflow/boundary_conditions/bc_array.py
boreflow/boundary_conditions/bc_base.py
boreflow/boundary_conditions/bc_overtopping.py
boreflow/boundary_conditions/bc_wos.py
boreflow/boundary_conditions/bc_wos_fd.py
boreflow/boundary_conditions/bc_wos_millingen.py
boreflow/boundary_conditions/bc_wos_tholen.py
boreflow-0.1.3.dist-info/METADATA
boreflow-0.1.3.dist-info/WHEEL
boreflow-0.1.3.dist-info/RECORD
