Metadata-Version: 2.4
Name: boreflow
Version: 0.1.3
Summary: Python package to simulate the flow of overtopping and bores.
Project-URL: Documentation, https://nielsvandervegt.github.io/boreflow
Project-URL: Source, https://github.com/nielsvandervegt/boreflow
Author: Niels van der Vegt
License: GNU-GPL V3
Requires-Dist: numpy
Requires-Dist: scipy
Requires-Dist: tqdm
